README.md
setup.py
GummyFNAsync/__init__.py
GummyFNAsync/cosmetics.py
GummyFNAsync/enums.py
GummyFNAsync/exceptions.py
GummyFNAsync.egg-info/PKG-INFO
GummyFNAsync.egg-info/SOURCES.txt
GummyFNAsync.egg-info/dependency_links.txt
GummyFNAsync.egg-info/requires.txt
GummyFNAsync.egg-info/top_level.txt