Metadata-Version: 2.1
Name: GummyFNAsync
Version: 1.0.0
Summary: Async Api wrapper for GummyFN
Home-page: https://api.gummyfn.com
Author: Pirxcy
License: UNKNOWN
Platform: UNKNOWN
Classifier: Programming Language :: Python :: 3
Classifier: License :: OSI Approved :: MIT License
Classifier: Operating System :: OS Independent
